[
    
  {  
    "imageUrl": "https://cdn.shopify.com/s/files/1/0565/8021/0861/files/Frame106722523_1.png?v=1704778003",
    "brand": "SKATRS ",
    "title": "SKATRS Adjustable Reflective Collar with Bell for Cats & Puppies (Lime Green)",
    "color": " Green",
    "discountedPrice": 199 ,
    "price": 149,
    "discountPersent": 25,
    "size": [
        {
          "name": "1",
          "quantity": 13
        },
        {
          "name": "3",
          "quantity": 17
        },
        {
          "name": "6",
          "quantity": 10
        }
      ],
      "quantity": 40,
      "topLavelCategory": "cats",
      "secondLavelCategory": "accessories",
      "thirdLavelCategory": "catcollars",
      "description":"The SKATRS Cat Collar with Bell, featuring a simple buckled design, is crafted from nylon, offering a commendable option, particularly suitable for feline and juvenile canine companions."
},
{  
    "imageUrl": "https://cdn.shopify.com/s/files/1/0565/8021/0861/products/1_35_1-207462.png?v=1696473357",
    "brand": "Basil ",
    "title": "Basil Printed Collar for Cats & Puppies (Orange)",
    "color": " Orange",
    "discountedPrice": 125 ,
    "price": 106,
    "discountPersent": 15,
    "size": [
        {
          "name": "1",
          "quantity": 7
        },
        {
          "name": "3",
          "quantity": 9
        },
        {
          "name": "6",
          "quantity": 8
        }
      ],
      "quantity": 24,
      "topLavelCategory": "cats",
      "secondLavelCategory": "accessories",
      "thirdLavelCategory": "catcollars",
      "description":"Cat collar from Basil for Pet is a comfort and durable collar for your pet. Suitable for cats and Small puppies."
},
{  
    "imageUrl": "https://cdn.shopify.com/s/files/1/0565/8021/0861/products/31SW-Xcu2eL1-467521.png?v=1696473621",
    "brand": "Basil",
    "title": "Basil Printed Collar for Cats & Puppies (Blue)",
    "color": "Blue ",
    "discountedPrice": 125 ,
    "price": 106,
    "discountPersent": 15,
    "size": [
        {
          "name": "1",
          "quantity": 15
        },
        {
          "name": "3",
          "quantity": 19
        },
        {
          "name": "6",
          "quantity": 9
        }
      ],
      "quantity": 43,
      "topLavelCategory": "cats",
      "secondLavelCategory": "accessories",
      "thirdLavelCategory": "catcollars",
      "description":"Cat collar from Basil for Pet is a comfort and durable collar for your pet. Suitable for cats and Small puppies."
},
{  
    "imageUrl": "https://cdn.shopify.com/s/files/1/0565/8021/0861/files/Image_8_1_1.png?v=1704361570",
    "brand": "SKATRS",
    "title": "SKATRS Adjustable Reflective Collar with Bell for Cats & Puppies (Red)",
    "color": " Red",
    "discountedPrice": 199 ,
    "price": 149,
    "discountPersent": 25,
    "size": [
        {
          "name": "1",
          "quantity": 7
        },
        {
          "name": "3",
          "quantity": 3
        },
        {
          "name": "6",
          "quantity": 8
        }
      ],
      "quantity": 18,
      "topLavelCategory": "cats",
      "secondLavelCategory": "accessories",
      "thirdLavelCategory": "catcollars",
      "description":"The SKATRS Cat Collar with Bell, featuring a simple buckled design, is crafted from nylon, offering a commendable option, particularly suitable for feline and juvenile canine companions."
},
{  
    "imageUrl": "https://cdn.shopify.com/s/files/1/0565/8021/0861/files/Frame12350_1ab72edf-f812-43e7-93ae-80ff1cebfdfa.png?v=1696625076",
    "brand": "Trixie",
    "title": "Trixie Safer Life Reflective Collar with Bell for Cats (Pink)",
    "color": "Pink ",
    "discountedPrice": 275 ,
    "price": 242,
    "discountPersent": 12,
    "size": [
        {
          "name": "1",
          "quantity": 20
        },
        {
          "name": "3",
          "quantity": 8
        },
        {
          "name": "6",
          "quantity": 4
        }
      ],
      "quantity": 32,
      "topLavelCategory": "cats",
      "secondLavelCategory": "accessories",
      "thirdLavelCategory": "catcollars",
      "description":"Our collars for cats are available in various versions, sizes and colours, with or without bell. "
},
{  
    "imageUrl": "https://cdn.shopify.com/s/files/1/0565/8021/0861/products/Frame1_56_9828601d-b62d-4473-9b91-f9d5117f3e46-635337.png?v=1696553722",
    "brand": "Jewel",
    "title": "M Pets Jewel Collar for Cats",
    "color": " ",
    "discountedPrice": 299 ,
    "price": 269,
    "discountPersent": 10,
    "size": [
        {
          "name": "1",
          "quantity": 16
        },
        {
          "name": "3",
          "quantity": 13
        },
        {
          "name": "6",
          "quantity": 12
        }
      ],
      "quantity": 41,
      "topLavelCategory": "cats",
      "secondLavelCategory": "accessories",
      "thirdLavelCategory": "catcollars",
      "description":"This adorable collar comes in more than one color option and allows your cat to safely explore the outdoors with the safety release clip and bell. Plus, with style and strength."
},
{  
    "imageUrl": "https://cdn.shopify.com/s/files/1/0565/8021/0861/files/Frame12004_f968454d-e103-4137-a73a-ea48a0bac058.png?v=1696619957",
    "brand": "Trixie",
    "title": "Trixie Elastic Collars with Bell for Cats (Black)",
    "color": " Black",
    "discountedPrice": 135 ,
    "price": 119,
    "discountPersent": 12,
    "size": [
        {
          "name": "1",
          "quantity": 12
        },
        {
          "name": "3",
          "quantity": 14
        },
        {
          "name": "6",
          "quantity": 9
        }
      ],
      "quantity": 35,
      "topLavelCategory": "cats",
      "secondLavelCategory": "accessories",
      "thirdLavelCategory": "catcollars",
      "description":"If you know how to bell the cat, then these cute cat collars from Trixie are just for you."
},
{  
    "imageUrl": "https://cdn.shopify.com/s/files/1/0565/8021/0861/products/1_36_1-821376.png?v=1696473672",
    "brand": "Basil",
    "title": "Basil Printed Collar for Cats & Puppies (Pink)",
    "color": " Pink",
    "discountedPrice": 125 ,
    "price": 113,
    "discountPersent": 10,
    "size": [
        {
          "name": "1",
          "quantity": 5
        },
        {
          "name": "3",
          "quantity": 3
        },
        {
          "name": "6",
          "quantity": 4
        }
      ],
      "quantity": 12,
      "topLavelCategory": "cats",
      "secondLavelCategory": "accessories",
      "thirdLavelCategory": "catcollars",
      "description":"Cat collar from Basil for Pet is a comfort and durable collar for your pet. Suitable for cats and Small puppies."
},
{  
    "imageUrl": "https://cdn.shopify.com/s/files/1/0565/8021/0861/products/1_39_1-692896.png?v=1696473653",
    "brand": "Basil",
    "title": "Basil Printed Collar for Cats & Puppies (Green)",
    "color": " Green",
    "discountedPrice": 125 ,
    "price": 113,
    "discountPersent": 10,
    "size": [
        {
          "name": "1",
          "quantity": 14
        },
        {
          "name": "3",
          "quantity": 12
        },
        {
          "name": "6",
          "quantity": 5
        }
      ],
      "quantity": 31,
      "topLavelCategory": "cats",
      "secondLavelCategory": "accessories",
      "thirdLavelCategory": "catcollars",
      "description":"Cat collar from Basil for Pet is a comfort and durable collar for your pet. Suitable for cats and Small puppies."
},
{  
    "imageUrl": "https://cdn.shopify.com/s/files/1/0565/8021/0861/files/Frame12371.png?v=1696554964",
    "brand": "Zany ",
    "title": "M Pets Zany Eco Collar for Cats (Blue)",
    "color": "Blue ",
    "discountedPrice": 299 ,
    "price": 269,
    "discountPersent": 10,
    "size": [
        {
          "name": "1",
          "quantity": 15
        },
        {
          "name": "3",
          "quantity": 14
        },
        {
          "name": "6",
          "quantity": 9
        }
      ],
      "quantity": 36,
      "topLavelCategory": "cats",
      "secondLavelCategory": "accessories",
      "thirdLavelCategory": "catcollars",
      "description":"This beautiful M-Pets Cat Collars - Eco Range Zany is easy to use and Pet friendly! The collar is made from 100% recycled bottles and is therefore environmentally friendly."
}
]